[
    {
        "nom": "DRHAT",
        "url": "https://www.sengager.fr/",
        "status": "UP",
        "detail": "OK",
        "last_check": "2026-02-14 07:08:00"
    },
    {
        "nom": "mangerbouger",
        "url": "https://www.mangerbouger.fr/",
        "status": "UP",
        "detail": "OK",
        "last_check": "2026-02-14 07:08:01"
    },
    {
        "nom": "santementale",
        "url": "https://www.santementale-info-service.fr",
        "status": "UP",
        "detail": "OK",
        "last_check": "2026-02-14 07:08:02"
    },
    {
        "nom": "tabac",
        "url": "https://www.tabac-info-service.fr",
        "status": "UP",
        "detail": "OK",
        "last_check": "2026-02-14 07:08:03"
    },
    {
        "nom": "Mois Sans Tabac",
        "url": "https://mois-sans-tabac.tabac-info-service.fr/",
        "status": "UP",
        "detail": "OK",
        "last_check": "2026-02-14 07:08:04"
    },
    {
        "nom": "vaccination",
        "url": "https://vaccination-info-service.fr",
        "status": "UP",
        "detail": "OK",
        "last_check": "2026-02-14 07:08:05"
    },
    {
        "nom": "alcool",
        "url": "https://www.alcool-info-service.fr/",
        "status": "UP",
        "detail": "OK",
        "last_check": "2026-02-14 07:08:06"
    },
    {
        "nom": "premiersjour",
        "url": "https://www.1000-premiers-jours.fr/fr",
        "status": "UP",
        "detail": "OK",
        "last_check": "2026-02-14 07:08:07"
    },
    {
        "nom": "marinenat",
        "url": "https://lamarinerecrute.gouv.fr/",
        "status": "UP",
        "detail": "OK",
        "last_check": "2026-02-14 07:08:08"
    },
    {
        "nom": "DRHAAE",
        "url": "https://devenir-aviateur.gouv.fr/",
        "status": "UP",
        "detail": "OK",
        "last_check": "2026-02-14 07:08:10"
    },
    {
        "nom": "ASC",
        "url": "https://www.service-civique.gouv.fr/",
        "status": "UP",
        "detail": "OK",
        "last_check": "2026-02-14 07:08:11"
    }
]